README.md
setup.py
bin/battleship
ex_battleship/__init__.py
ex_battleship/ex_battleship.py
ex_battleship.egg-info/PKG-INFO
ex_battleship.egg-info/SOURCES.txt
ex_battleship.egg-info/dependency_links.txt
ex_battleship.egg-info/top_level.txt